.mina/adapter_onebot11.toml
satori/adapters/onebot11/__init__.py
satori/adapters/onebot11/api.py
satori/adapters/onebot11/events/__init__.py
satori/adapters/onebot11/events/base.py
satori/adapters/onebot11/events/message.py
satori/adapters/onebot11/events/notice.py
satori/adapters/onebot11/events/request.py
satori/adapters/onebot11/forward.py
satori/adapters/onebot11/message.py
satori/adapters/onebot11/reverse.py
satori/adapters/onebot11/utils.py
satori_python_adapter_onebot11-0.2.7.dist-info/METADATA
satori_python_adapter_onebot11-0.2.7.dist-info/WHEEL
satori_python_adapter_onebot11-0.2.7.dist-info/licenses/LICENSE
satori_python_adapter_onebot11-0.2.7.dist-info/RECORD
