Metadata-Version: 2.1
Name: satori-python-adapter-onebot11
Version: 0.2.7
Summary: Satori Protocol SDK for python, adapter for OneBot 11
Home-page: https://github.com/RF-Tar-Railt/satori-python
Author-Email: RF-Tar-Railt <rf_tar_railt@qq.com>
License: MIT
Classifier: Typing :: Typed
Classifier: Development Status :: 4 - Beta
Classifier: License :: OSI Approved :: MIT License
Classifier: Programming Language :: Python :: 3.8
Classifier: Programming Language :: Python :: 3.9
Classifier: Programming Language :: Python :: 3.10
Classifier: Programming Language :: Python :: 3.11
Classifier: Programming Language :: Python :: 3.12
Classifier: Operating System :: OS Independent
Project-URL: Homepage, https://github.com/RF-Tar-Railt/satori-python
Project-URL: Repository, https://github.com/RF-Tar-Railt/satori-python
Requires-Python: <4.0,>=3.10
Requires-Dist: satori-python-server>=0.17.6
